py_vsk/__init__.py
py_vsk/py_vsk.py
py_vsk-0.0.8.dist-info/LICENSE.txt
py_vsk-0.0.8.dist-info/METADATA
py_vsk-0.0.8.dist-info/WHEEL
py_vsk-0.0.8.dist-info/top_level.txt
py_vsk-0.0.8.dist-info/RECORD
