Metadata-Version: 2.1
Name: py-vsk
Version: 0.0.8
Summary: Python Functions for Vasicek Distribution
Home-page: https://github.com/statcompute/py_vsk
Author: WenSui Liu
Author-email: liuwensui@gmail.com
License: UNKNOWN
Platform: UNKNOWN
Classifier: Programming Language :: Python :: 3
Classifier: License :: OSI Approved :: MIT License
Classifier: Operating System :: OS Independent
Requires-Dist: py-mob
Requires-Dist: scipy
Requires-Dist: numpy
Requires-Dist: statsmodels
